datashift/__init__.py
datashift/cli.py
datashift/config.py
datashift/diffing.py
datashift/experiment.py
datashift/integrations/__init__.py
datashift/integrations/torch.py
datashift/ipython.py
datashift/metadata.py
datashift/migrations.py
datashift/storage.py
datashift/versioning.py
hyper_flux_data_shift-0.1.0.dist-info/entry_points.txt
hyper_flux_data_shift-0.1.0.dist-info/licenses/LICENSE
hyper_flux_data_shift-0.1.0.dist-info/METADATA
hyper_flux_data_shift-0.1.0.dist-info/WHEEL
hyper_flux_data_shift-0.1.0.dist-info/RECORD
