Metadata-Version: 2.4
Name: hyper-flux-data-shift
Version: 0.1.0
Summary: Dataset versioning and migration framework for ML data
License-File: LICENSE
Author: DataShift Team
Author-email: team@datashift.ai
Requires-Python: >=3.10
Classifier: Programming Language :: Python :: 3
Classifier: Programming Language :: Python :: 3.10
Classifier: Programming Language :: Python :: 3.11
Classifier: Programming Language :: Python :: 3.12
Classifier: Programming Language :: Python :: 3.13
Classifier: Programming Language :: Python :: 3.14
Provides-Extra: all
Provides-Extra: parquet
Provides-Extra: torch
Requires-Dist: fastparquet (>=2023.1.0) ; extra == "parquet" or extra == "all"
Requires-Dist: pandas (>=2.0.0)
Requires-Dist: pyarrow (>=10.0.0) ; extra == "parquet" or extra == "all"
Requires-Dist: torch (>=2.0.0) ; extra == "torch" or extra == "all"
